intputlib/__init__.py
intputlib/core.py
intputlib-1.1.3.dist-info/licenses/LICENSE
intputlib-1.1.3.dist-info/METADATA
intputlib-1.1.3.dist-info/WHEEL
intputlib-1.1.3.dist-info/top_level.txt
intputlib-1.1.3.dist-info/RECORD
