Metadata-Version: 2.4
Name: intputlib
Version: 1.1.3
Summary: A simple helper function for reading integers and floats from input
Author-email: Kayk Caputo <caputo.kayk@gmail.com>
License: MIT
Requires-Python: >=3.8
License-File: LICENSE
Dynamic: license-file
